PySeismoSoil/__init__.py
PySeismoSoil/class_Vs_profile.py
PySeismoSoil/class_batch_simulation.py
PySeismoSoil/class_curves.py
PySeismoSoil/class_damping_calibration.py
PySeismoSoil/class_frequency_spectrum.py
PySeismoSoil/class_gof_scores.py
PySeismoSoil/class_ground_motion.py
PySeismoSoil/class_hh_calibration.py
PySeismoSoil/class_parameters.py
PySeismoSoil/class_simulation.py
PySeismoSoil/class_simulation_results.py
PySeismoSoil/class_site_effect_adjustment.py
PySeismoSoil/class_site_factors.py
PySeismoSoil/class_svm.py
PySeismoSoil/helper_generic.py
PySeismoSoil/helper_gof_scores.py
PySeismoSoil/helper_hh_calibration.py
PySeismoSoil/helper_hh_model.py
PySeismoSoil/helper_mkz_model.py
PySeismoSoil/helper_signal_processing.py
PySeismoSoil/helper_simulations.py
PySeismoSoil/helper_site_response.py
PySeismoSoil/data/amplification/175_008_af_fs_eq_hh_avg.csv
PySeismoSoil/data/amplification/175_008_af_fs_eq_hh_std.csv
PySeismoSoil/data/amplification/175_008_af_fs_nl_hh_avg.csv
PySeismoSoil/data/amplification/175_008_af_fs_nl_hh_std.csv
PySeismoSoil/data/amplification/175_008_af_rs_eq_hh_avg.csv
PySeismoSoil/data/amplification/175_008_af_rs_eq_hh_std.csv
PySeismoSoil/data/amplification/175_008_af_rs_nl_hh_avg.csv
PySeismoSoil/data/amplification/175_008_af_rs_nl_hh_std.csv
PySeismoSoil/data/amplification/175_008_freq.csv
PySeismoSoil/data/amplification/175_008_period.csv
PySeismoSoil/data/amplification/175_016_af_fs_eq_hh_avg.csv
PySeismoSoil/data/amplification/175_016_af_fs_eq_hh_std.csv
PySeismoSoil/data/amplification/175_016_af_fs_nl_hh_avg.csv
PySeismoSoil/data/amplification/175_016_af_fs_nl_hh_std.csv
PySeismoSoil/data/amplification/175_016_af_rs_eq_hh_avg.csv
PySeismoSoil/data/amplification/175_016_af_rs_eq_hh_std.csv
PySeismoSoil/data/amplification/175_016_af_rs_nl_hh_avg.csv
PySeismoSoil/data/amplification/175_016_af_rs_nl_hh_std.csv
PySeismoSoil/data/amplification/175_016_freq.csv
PySeismoSoil/data/amplification/175_016_period.csv
pyseismosoil-0.6.3.dist-info/licenses/LICENSE
pyseismosoil-0.6.3.dist-info/METADATA
pyseismosoil-0.6.3.dist-info/WHEEL
pyseismosoil-0.6.3.dist-info/top_level.txt
pyseismosoil-0.6.3.dist-info/RECORD
