Metadata-Version: 2.4
Name: PySeismoSoil
Version: 0.6.3
Summary: A Python library for performing 1D seismic site response analysis
Author: PySeismoSoil Contributors
License: BSD-3-Clause
Project-URL: Homepage, https://caltech-geoquake.github.io/PySeismoSoil/
Classifier: License :: OSI Approved :: BSD License
Classifier: Programming Language :: Python :: 3
Classifier: Programming Language :: Python :: 3 :: Only
Requires-Python: >=3.10
License-File: LICENSE
Requires-Dist: matplotlib>=2.0.0
Requires-Dist: numba>=0.38.0
Requires-Dist: numpy>=1.11.0
Requires-Dist: scipy>=1.1.0
Requires-Dist: PyWavelets>=1.3.0
Dynamic: license-file
